poetry_version_from_file/plugin.py
poetry_version_from_file-1.1.0.dist-info/LICENSE
poetry_version_from_file-1.1.0.dist-info/METADATA
poetry_version_from_file-1.1.0.dist-info/WHEEL
poetry_version_from_file-1.1.0.dist-info/entry_points.txt
poetry_version_from_file-1.1.0.dist-info/RECORD
