Metadata-Version: 2.1
Name: poetry-version-from-file
Version: 1.1.0
Summary: 
Home-page: https://github.com/tobiasge/poetry-version-from-file
License: MIT
Keywords: packaging,poetry-plugin,poetry
Author: Tobias Genannt
Author-email: tobias.genannt@gmail.com
Requires-Python: >=3.9,<4.0
Classifier: Development Status :: 5 - Production/Stable
Classifier: License :: OSI Approved :: MIT License
Classifier: Programming Language :: Python :: 3
Classifier: Programming Language :: Python :: 3.9
Classifier: Programming Language :: Python :: 3.10
Classifier: Programming Language :: Python :: 3.11
Classifier: Programming Language :: Python :: 3.12
Classifier: Topic :: Software Development :: Build Tools
Requires-Dist: poetry (>=1.8,<2.0)
Project-URL: Bug Tracker, https://github.com/tobiasge/poetry-version-from-file/issues
